{
    "toolbar": "#toolbar",
    "search": "true",
    "searchable": "true",
    "idfield": "pk",
    "showFooter": "true",
    "pagination": "true",
    "pageList":"[10,25,50,100,all]",
    "pageSize": "5",
    "data": [],
    "onClickRow": "",
    "columns": [
        {
            "field": "KS-Serial",
            "title": "#",
            "formatter": "jFLocalSerialColumn"
        },
        {
            "field": "QrCodeId",
            "title": "Qr",
            "width": "100"
        },
        {
            "field": "OrderNumber",
            "title": "Ord_ID"
        },
        {
            "title": "Branch",
            "field": "BranchName",
            "width": "200"
        },
        {
            "field": "ItemName",
            "title": "Item",
            "width": "300"
        },
        {
            "title": "TimeSpan",
            "field": "TimeSpan"
        },
        {
            "title": "Rate",
            "field": "Rate",
            "width": "200",
            "align":"right",
            "filtercontrol": "select",
            "formatter": "",
            "footerFormatter":""
        },
        {
            "field": "OrderNo",
            "title": "Order",
            "width": "100"
        },
        {
            "field": "BranchScan_DC",
            "title": "Branch DC",
            "width": "100"
        },
        {
            "field": "location",
            "title": "Location"
        },
        {
            "field": "BranchScan_FactoryName",
            "title": "Factory",
            "width": "200"
        },
        {
            "field": "CustomerName",
            "title": "Customer"
        },
        {
            "field": "CustomerMobileNumber",
            "title": "Mobile"
        }
    ]
}